README.txt
setup.cfg
setup.py
bonner_nacht/__init__.py
bonner_nacht.theme.egg-info/PKG-INFO
bonner_nacht.theme.egg-info/SOURCES.txt
bonner_nacht.theme.egg-info/dependency_links.txt
bonner_nacht.theme.egg-info/namespace_packages.txt
bonner_nacht.theme.egg-info/not-zip-safe
bonner_nacht.theme.egg-info/requires.txt
bonner_nacht.theme.egg-info/top_level.txt
bonner_nacht/theme/__init__.py
bonner_nacht/theme/configure.zcml
bonner_nacht/theme/profiles/default/cssregistry.xml
bonner_nacht/theme/profiles/default/jsregistry.xml
bonner_nacht/theme/profiles/default/metadata.xml
bonner_nacht/theme/profiles/default/theme.xml
bonner_nacht/theme/resources/index.html
bonner_nacht/theme/resources/manifest.cfg
bonner_nacht/theme/resources/rules.xml
bonner_nacht/theme/resources/css/desktop.css
bonner_nacht/theme/resources/css/fonts.css
bonner_nacht/theme/resources/css/icons.css
bonner_nacht/theme/resources/css/menu.css
bonner_nacht/theme/resources/css/mobile.css
bonner_nacht/theme/resources/img/assets/arw_left.svg
bonner_nacht/theme/resources/img/assets/arw_left_inv.svg
bonner_nacht/theme/resources/img/assets/arw_right.svg
bonner_nacht/theme/resources/img/assets/arw_right_inv.svg
bonner_nacht/theme/resources/img/backgrounds/LICENSE.txt
bonner_nacht/theme/resources/img/backgrounds/background.jpg
bonner_nacht/theme/resources/js/browser-support.js
bonner_nacht/theme/resources/js/checkout-external.sh
bonner_nacht/theme/resources/js/hide-description.js
bonner_nacht/theme/resources/js/install-webapp.js
bonner_nacht/theme/resources/js/piwik-tracking.js
bonner_nacht/theme/resources/js/3rdparty/noty/jquery.noty.js
bonner_nacht/theme/resources/js/3rdparty/noty/layouts/top.js
bonner_nacht/theme/resources/js/3rdparty/noty/themes/default.js
bonner_nacht/theme/resources/otf/Herr_Von_Muellerhoff/HerrVonMuellerhoff-Regular.ttf
bonner_nacht/theme/resources/otf/Herr_Von_Muellerhoff/OFL.txt
bonner_nacht/theme/resources/otf/Merriweather/Merriweather-Black.ttf
bonner_nacht/theme/resources/otf/Merriweather/Merriweather-Bold.ttf
bonner_nacht/theme/resources/otf/Merriweather/Merriweather-BoldItalic.ttf
bonner_nacht/theme/resources/otf/Merriweather/Merriweather-HeavyItalic.ttf
bonner_nacht/theme/resources/otf/Merriweather/Merriweather-Italic.ttf
