Metadata-Version: 1.1
Name: bonner-nacht.theme
Version: 1.2.0
Summary: Theme for the Bonner Nacht website
Home-page: http://www.bonner-nacht.de
Author: Fabian Köster
Author-email: koesterreich@fastmail.fm
License: AGPL
Platform: UNKNOWN
Classifier: Framework :: Plone
Classifier: Programming Language :: Python
